[
  {
    "name": "Termitidae",
    "start": 2407,
    "end": 2417
  },
  {
    "name": "Rhinotermitidae",
    "start": 2529,
    "end": 2544
  },
  {
    "name": "Coptotermes gambrinus",
    "start": 2696,
    "end": 2717
  },
  {
    "name": "Parrhinotermes barbatus",
    "start": 2722,
    "end": 2745
  },
  {
    "name": "Heterotermes",
    "start": 2777,
    "end": 2789
  },
  {
    "name": "Coptotermes",
    "start": 2977,
    "end": 2988
  },
  {
    "name": "Schedorhinotermes",
    "start": 2993,
    "end": 3010
  },
  {
    "name": "Schedolimulus minutides",
    "start": 3218,
    "end": 3241
  },
  {
    "name": "Schedolimulus minutus",
    "start": 3303,
    "end": 3324
  },
  {
    "name": "Rhinotermitidae",
    "start": 3643,
    "end": 3658
  },
  {
    "name": "Mesotermitidae",
    "start": 3789,
    "end": 3803
  },
  {
    "name": "Rhinotermitidae",
    "start": 3847,
    "end": 3862
  },
  {
    "name": "Stylotermitidae",
    "start": 4091,
    "end": 4106
  },
  {
    "name": "Serritermitidae",
    "start": 4111,
    "end": 4126
  },
  {
    "name": "Rhinotermitidae",
    "start": 4264,
    "end": 4279
  },
  {
    "name": "Prorhinotermes",
    "start": 4341,
    "end": 4355
  },
  {
    "name": "Termitogeton",
    "start": 4357,
    "end": 4369
  },
  {
    "name": "Psammotermes",
    "start": 4374,
    "end": 4386
  },
  {
    "name": "Rhinotermitinae",
    "start": 4427,
    "end": 4442
  },
  {
    "name": "Parrhinotermes",
    "start": 4454,
    "end": 4468
  },
  {
    "name": "Schedorhinotermes",
    "start": 4470,
    "end": 4487
  },
  {
    "name": "Rhinotermes",
    "start": 4508,
    "end": 4519
  },
  {
    "name": "Heterotermitinae",
    "start": 4536,
    "end": 4552
  },
  {
    "name": "Coptotermitinae",
    "start": 4555,
    "end": 4570
  },
  {
    "name": "Reticulitermes",
    "start": 4583,
    "end": 4597
  },
  {
    "name": "Heterotermes",
    "start": 4599,
    "end": 4611
  },
  {
    "name": "Coptotermes",
    "start": 4616,
    "end": 4627
  },
  {
    "name": "Rhinotermitidae",
    "start": 4655,
    "end": 4670
  },
  {
    "name": "Serritermitidae",
    "start": 4719,
    "end": 4734
  },
  {
    "name": "Termitidae",
    "start": 4738,
    "end": 4748
  },
  {
    "name": "Rhinotermitidae",
    "start": 4881,
    "end": 4896
  },
  {
    "name": "Prorhinotermes",
    "start": 5006,
    "end": 5020
  },
  {
    "name": "Coptotermes",
    "start": 5131,
    "end": 5142
  },
  {
    "name": "Termitogeton",
    "start": 5168,
    "end": 5180
  },
  {
    "name": "Schedorhinotermes",
    "start": 5217,
    "end": 5234
  },
  {
    "name": "Rhinotermitidae",
    "start": 5260,
    "end": 5275
  },
  {
    "name": "Parrhinotermes",
    "start": 5307,
    "end": 5321
  },
  {
    "name": "Schedorhinotermes",
    "start": 5323,
    "end": 5340
  },
  {
    "name": "Coptotermes",
    "start": 5342,
    "end": 5353
  },
  {
    "name": "Heterotermes",
    "start": 5355,
    "end": 5367
  },
  {
    "name": "Prorhinotermes",
    "start": 5369,
    "end": 5383
  },
  {
    "name": "Termitogeton",
    "start": 5388,
    "end": 5400
  },
  {
    "name": "Rhinotermitinae",
    "start": 5493,
    "end": 5508
  },
  {
    "name": "Rhinotermitidae",
    "start": 6016,
    "end": 6031
  },
  {
    "name": "Coptotermes elisae",
    "start": 6368,
    "end": 6386
  },
  {
    "name": "Coptotermes obiratus",
    "start": 6404,
    "end": 6424
  },
  {
    "name": "Schedorhinotermes dimorphus",
    "start": 6437,
    "end": 6464
  },
  {
    "name": "Schedorhinotermes translucens",
    "start": 6482,
    "end": 6511
  },
  {
    "name": "Schedorhinotermes celebensis",
    "start": 6534,
    "end": 6562
  },
  {
    "name": "Prorhinotermes inopinatus",
    "start": 6582,
    "end": 6607
  },
  {
    "name": "Prorhinotermes",
    "start": 6688,
    "end": 6702
  },
  {
    "name": "Prorhinotermes inopinatus",
    "start": 6718,
    "end": 6743
  },
  {
    "name": "Parrhinotermes",
    "start": 6746,
    "end": 6760
  },
  {
    "name": "Parrhinotermes browni",
    "start": 6765,
    "end": 6786
  },
  {
    "name": "Termitogeton",
    "start": 6807,
    "end": 6819
  },
  {
    "name": "Termitogeton",
    "start": 6824,
    "end": 6836
  },
  {
    "name": "Termitidae",
    "start": 7304,
    "end": 7314
  },
  {
    "name": "Coptotermes",
    "start": 11773,
    "end": 11784
  },
  {
    "name": "Termes",
    "start": 11864,
    "end": 11870
  },
  {
    "name": "Coptotermes",
    "start": 11872,
    "end": 11883
  },
  {
    "name": "Termes gestroi",
    "start": 12013,
    "end": 12027
  },
  {
    "name": "Coptotermes",
    "start": 12817,
    "end": 12828
  },
  {
    "name": "Coptotermes formosanus",
    "start": 13133,
    "end": 13155
  },
  {
    "name": "Coptotermes elisae",
    "start": 13292,
    "end": 13310
  },
  {
    "name": "Termes",
    "start": 13444,
    "end": 13450
  },
  {
    "name": "Coptotermes",
    "start": 13452,
    "end": 13463
  },
  {
    "name": "Coptotermes Elisae",
    "start": 13515,
    "end": 13533
  },
  {
    "name": "Coptotermes hyaloapex",
    "start": 13588,
    "end": 13609
  },
  {
    "name": "Erythrina",
    "start": 14082,
    "end": 14091
  },
  {
    "name": "Araucaria cunninghammi",
    "start": 14604,
    "end": 14626
  },
  {
    "name": "Coptotermes elisae",
    "start": 16126,
    "end": 16144
  },
  {
    "name": "Coptotermes elisae",
    "start": 17556,
    "end": 17574
  },
  {
    "name": "Coptotermes hyaloapex",
    "start": 18069,
    "end": 18090
  },
  {
    "name": "Coptophysa obesa",
    "start": 18318,
    "end": 18334
  },
  {
    "name": "Coleoptera",
    "start": 18336,
    "end": 18346
  },
  {
    "name": "Staphylinidae",
    "start": 18348,
    "end": 18361
  },
  {
    "name": "Coptotermes remotus",
    "start": 18526,
    "end": 18545
  },
  {
    "name": "Coptotermes remotus",
    "start": 18676,
    "end": 18695
  },
  {
    "name": "Coptotermes remotus",
    "start": 20127,
    "end": 20146
  },
  {
    "name": "Coptotermes remotus",
    "start": 21706,
    "end": 21725
  },
  {
    "name": "Coptotermes lacteus",
    "start": 21764,
    "end": 21783
  },
  {
    "name": "Coptotermes bentongensis",
    "start": 21805,
    "end": 21829
  },
  {
    "name": "Coptotermes sepangensis",
    "start": 21834,
    "end": 21857
  },
  {
    "name": "Coptotermes remotus",
    "start": 21986,
    "end": 22005
  },
  {
    "name": "Coptophysella pulposa",
    "start": 22550,
    "end": 22571
  },
  {
    "name": "Coleoptera",
    "start": 22573,
    "end": 22583
  },
  {
    "name": "Staphylinidae",
    "start": 22585,
    "end": 22598
  },
  {
    "name": "Coptophysella",
    "start": 22717,
    "end": 22730
  },
  {
    "name": "Coptotermes grandiceps",
    "start": 22878,
    "end": 22900
  },
  {
    "name": "Coptotermes grandiceps",
    "start": 23033,
    "end": 23055
  },
  {
    "name": "Coptotermes solomonensis",
    "start": 23098,
    "end": 23122
  },
  {
    "name": "Coptotermes obiratus",
    "start": 23197,
    "end": 23217
  },
  {
    "name": "Coptotermes solomonensis",
    "start": 23271,
    "end": 23295
  },
  {
    "name": "Coptotermes solomonensis",
    "start": 23337,
    "end": 23361
  },
  {
    "name": "Coptotermes froggatti",
    "start": 23426,
    "end": 23447
  },
  {
    "name": "Coptotermes obiratus",
    "start": 23710,
    "end": 23730
  },
  {
    "name": "Coptotermes grandiceps",
    "start": 25035,
    "end": 25057
  },
  {
    "name": "Coptotermes grandiceps",
    "start": 25423,
    "end": 25445
  },
  {
    "name": "Coptotermes obiratus",
    "start": 25450,
    "end": 25470
  },
  {
    "name": "Coptotermes obiratus",
    "start": 25651,
    "end": 25671
  },
  {
    "name": "Coptotermes grandiceps",
    "start": 25695,
    "end": 25717
  },
  {
    "name": "Coptotermes obiratus",
    "start": 26537,
    "end": 26557
  },
  {
    "name": "Coptotermes grandiceps",
    "start": 26593,
    "end": 26615
  },
  {
    "name": "Coptotermes pamuae",
    "start": 27032,
    "end": 27050
  },
  {
    "name": "Coptotermes grandiceps",
    "start": 27236,
    "end": 27258
  },
  {
    "name": "Coptotermes pamuae",
    "start": 27443,
    "end": 27461
  },
  {
    "name": "Coptotermes pamuae",
    "start": 27594,
    "end": 27612
  },
  {
    "name": "Coptotermes pamuae",
    "start": 29021,
    "end": 29039
  },
  {
    "name": "Coptotermes grandiceps",
    "start": 29347,
    "end": 29369
  },
  {
    "name": "Coptotermes acinaciformis",
    "start": 29619,
    "end": 29644
  },
  {
    "name": "Coptotermes pamuae",
    "start": 29754,
    "end": 29772
  },
  {
    "name": "Coptotermes grandiceps",
    "start": 29778,
    "end": 29800
  },
  {
    "name": "Coptotermes gambrinus",
    "start": 30210,
    "end": 30231
  },
  {
    "name": "Araucaria hunsteinii",
    "start": 30484,
    "end": 30504
  },
  {
    "name": "Coptotermes gambrinus",
    "start": 31827,
    "end": 31848
  },
  {
    "name": "Coptotermes elisae",
    "start": 32124,
    "end": 32142
  },
  {
    "name": "Coptotermes grandiceps",
    "start": 32152,
    "end": 32174
  },
  {
    "name": "Coptotermes gambrinus",
    "start": 32378,
    "end": 32399
  },
  {
    "name": "Coptotermes pamuae",
    "start": 32403,
    "end": 32421
  },
  {
    "name": "Coptotermes remotus",
    "start": 32426,
    "end": 32445
  },
  {
    "name": "Coptotermes remotus",
    "start": 32469,
    "end": 32488
  },
  {
    "name": "Coptotermes remotus",
    "start": 32682,
    "end": 32701
  },
  {
    "name": "Gambrinus",
    "start": 33073,
    "end": 33082
  },
  {
    "name": "Heterotermes",
    "start": 33253,
    "end": 33265
  },
  {
    "name": "Heterotermes",
    "start": 33346,
    "end": 33358
  },
  {
    "name": "Heterotermes platycephalus",
    "start": 33488,
    "end": 33514
  },
  {
    "name": "Heterotermes",
    "start": 34356,
    "end": 34368
  },
  {
    "name": "Heterotermes vagus",
    "start": 34708,
    "end": 34726
  },
  {
    "name": "Leucotermes vagus",
    "start": 34859,
    "end": 34876
  },
  {
    "name": "Heterotermes vagus",
    "start": 34919,
    "end": 34937
  },
  {
    "name": "Leucotermes venustus",
    "start": 34990,
    "end": 35010
  },
  {
    "name": "Heterotermes venustus",
    "start": 35064,
    "end": 35085
  },
  {
    "name": "Heterotermes venustus",
    "start": 35368,
    "end": 35389
  },
  {
    "name": "Heterotermes venustus",
    "start": 35795,
    "end": 35816
  },
  {
    "name": "Heterotermes vagus",
    "start": 35821,
    "end": 35839
  },
  {
    "name": "Heterotermes venustus",
    "start": 35880,
    "end": 35901
  },
  {
    "name": "Heterotermes vagus",
    "start": 36196,
    "end": 36214
  },
  {
    "name": "Heterotermes vagus",
    "start": 36300,
    "end": 36318
  },
  {
    "name": "Heterotermes vagus",
    "start": 37101,
    "end": 37119
  },
  {
    "name": "Heterotermes venustus",
    "start": 37134,
    "end": 37155
  },
  {
    "name": "Heterotermes paradoxus",
    "start": 37793,
    "end": 37815
  },
  {
    "name": "Termes paradoxus",
    "start": 37949,
    "end": 37965
  },
  {
    "name": "Heterotermes paradoxus",
    "start": 38011,
    "end": 38033
  },
  {
    "name": "Heterotermes paradoxus",
    "start": 39108,
    "end": 39130
  },
  {
    "name": "Heterotermes vagus",
    "start": 39493,
    "end": 39511
  },
  {
    "name": "Heterotermes paradoxus",
    "start": 39515,
    "end": 39537
  },
  {
    "name": "Heterotermes paradoxus",
    "start": 40770,
    "end": 40792
  },
  {
    "name": "Heterotermes paradoxus",
    "start": 40856,
    "end": 40878
  },
  {
    "name": "Heterotermes vagus",
    "start": 40892,
    "end": 40910
  },
  {
    "name": "Parrhinotermes",
    "start": 41493,
    "end": 41507
  },
  {
    "name": "Parrhinotermes",
    "start": 41588,
    "end": 41602
  },
  {
    "name": "Termes aequalis",
    "start": 41733,
    "end": 41748
  },
  {
    "name": "Termes aqualis",
    "start": 41781,
    "end": 41795
  },
  {
    "name": "Parrhinotermes browni",
    "start": 42926,
    "end": 42947
  },
  {
    "name": "Schedorhinotermes browni",
    "start": 43082,
    "end": 43106
  },
  {
    "name": "Parrhinotermes browni",
    "start": 43148,
    "end": 43169
  },
  {
    "name": "Araucaria cunninghamii",
    "start": 44352,
    "end": 44374
  },
  {
    "name": "Parrhinotermes browni",
    "start": 44972,
    "end": 44993
  },
  {
    "name": "Parrhinotermes barbatus",
    "start": 45281,
    "end": 45304
  },
  {
    "name": "Parrhinotermes browni",
    "start": 45634,
    "end": 45655
  },
  {
    "name": "Parrhinotermes barbatus",
    "start": 45659,
    "end": 45682
  },
  {
    "name": "Trichopseniini",
    "start": 47246,
    "end": 47260
  },
  {
    "name": "Coleptera",
    "start": 47262,
    "end": 47271
  },
  {
    "name": "Staphylinidae",
    "start": 47273,
    "end": 47286
  },
  {
    "name": "Parrhinopsenius brevipilosus",
    "start": 47347,
    "end": 47375
  },
  {
    "name": "Parrhinopsenius longipilosus",
    "start": 47377,
    "end": 47405
  },
  {
    "name": "Parrhinopsenius hirsutus",
    "start": 47407,
    "end": 47431
  },
  {
    "name": "Parrhinopsenius parvus",
    "start": 47433,
    "end": 47455
  },
  {
    "name": "Schedolimulus latus",
    "start": 47477,
    "end": 47496
  },
  {
    "name": "Parrhinotermes barbatus",
    "start": 47578,
    "end": 47601
  },
  {
    "name": "Parrhinotermes browni",
    "start": 49527,
    "end": 49548
  },
  {
    "name": "Parrhinotermes queenslandicus",
    "start": 49553,
    "end": 49582
  },
  {
    "name": "Parrhinopsenius",
    "start": 49970,
    "end": 49985
  },
  {
    "name": "Parrhinotermes browni",
    "start": 49997,
    "end": 50018
  },
  {
    "name": "Parrhinotermes",
    "start": 50080,
    "end": 50094
  },
  {
    "name": "Schedorhinotermes",
    "start": 50447,
    "end": 50464
  },
  {
    "name": "Rhinotermes",
    "start": 50546,
    "end": 50557
  },
  {
    "name": "Schedorhinotermes",
    "start": 50559,
    "end": 50576
  },
  {
    "name": "Schedorhinotermes",
    "start": 50623,
    "end": 50640
  },
  {
    "name": "Rhinotermes intermedius",
    "start": 50779,
    "end": 50802
  },
  {
    "name": "Parrhinotermes",
    "start": 50960,
    "end": 50974
  },
  {
    "name": "Schedorhinotermes seclusus",
    "start": 51264,
    "end": 51290
  },
  {
    "name": "Schedorhinotermes seclusus",
    "start": 52494,
    "end": 52520
  },
  {
    "name": "Rhinotermes",
    "start": 52653,
    "end": 52664
  },
  {
    "name": "Schedorhinotermes",
    "start": 52666,
    "end": 52683
  },
  {
    "name": "Schedorhinotermes intermedius seclusus",
    "start": 52744,
    "end": 52782
  },
  {
    "name": "Schedorhinotermes seclusus",
    "start": 52832,
    "end": 52858
  },
  {
    "name": "Schedorhinotermes seclusus",
    "start": 53836,
    "end": 53862
  },
  {
    "name": "Trichopseniini",
    "start": 56412,
    "end": 56426
  },
  {
    "name": "Coleoptera",
    "start": 56428,
    "end": 56438
  },
  {
    "name": "Staphylinidae",
    "start": 56440,
    "end": 56453
  },
  {
    "name": "Aleocharinae",
    "start": 56455,
    "end": 56467
  },
  {
    "name": "Schedolimulus seclusi",
    "start": 56513,
    "end": 56534
  },
  {
    "name": "Schedolimulus planus",
    "start": 56536,
    "end": 56556
  },
  {
    "name": "Papuapsenius magnus",
    "start": 56561,
    "end": 56580
  },
  {
    "name": "Schedorhinotermes malaccensis",
    "start": 56662,
    "end": 56691
  },
  {
    "name": "Rhinotermes",
    "start": 56828,
    "end": 56839
  },
  {
    "name": "Schedorhinotermes",
    "start": 56841,
    "end": 56858
  },
  {
    "name": "Schedorhinotermes malaccensis",
    "start": 56915,
    "end": 56944
  },
  {
    "name": "Schedorhinotermes malaccensis",
    "start": 58087,
    "end": 58116
  },
  {
    "name": "Schedorhinotermes longirostris",
    "start": 59611,
    "end": 59641
  },
  {
    "name": "Termes longirostris",
    "start": 59776,
    "end": 59795
  },
  {
    "name": "Rhinotermes",
    "start": 59837,
    "end": 59848
  },
  {
    "name": "Schedorhinotermes",
    "start": 59850,
    "end": 59867
  },
  {
    "name": "Schedorhinotermes longirostris",
    "start": 59935,
    "end": 59965
  },
  {
    "name": "Rhinotermes dimorphus",
    "start": 60017,
    "end": 60038
  },
  {
    "name": "Rhinotermes",
    "start": 60090,
    "end": 60101
  },
  {
    "name": "Schedorhinotermes",
    "start": 60103,
    "end": 60120
  },
  {
    "name": "Schedorhinotermes dimorphus",
    "start": 60186,
    "end": 60213
  },
  {
    "name": "Schedorhinotermes dimorphus",
    "start": 60451,
    "end": 60478
  },
  {
    "name": "Schedorhinotermes longirostris",
    "start": 63437,
    "end": 63467
  },
  {
    "name": "Schedorhinotermes dimorphus",
    "start": 63472,
    "end": 63499
  },
  {
    "name": "Schedorhinotermes dimorphus",
    "start": 63637,
    "end": 63664
  },
  {
    "name": "Schedorhinotermes longirostris",
    "start": 63688,
    "end": 63718
  },
  {
    "name": "Schedorhinotermes longirostris",
    "start": 63804,
    "end": 63834
  },
  {
    "name": "Schedorhinotermes longirostris",
    "start": 65184,
    "end": 65214
  },
  {
    "name": "Schedorhinotermes dimorphus",
    "start": 65257,
    "end": 65284
  },
  {
    "name": "Schedorhinotermes longirostris",
    "start": 66200,
    "end": 66230
  },
  {
    "name": "Schedorhinotermes dimorphus",
    "start": 66276,
    "end": 66303
  },
  {
    "name": "Aleocharinae",
    "start": 67164,
    "end": 67176
  },
  {
    "name": "Coleoptera",
    "start": 67178,
    "end": 67188
  },
  {
    "name": "Staphylinidae",
    "start": 67190,
    "end": 67203
  },
  {
    "name": "Schedotermoecia kaimanensis",
    "start": 67235,
    "end": 67262
  },
  {
    "name": "Coptotermoeciina",
    "start": 67264,
    "end": 67280
  },
  {
    "name": "Schedotermoecia papuana",
    "start": 67335,
    "end": 67358
  },
  {
    "name": "Trichopseniini",
    "start": 67419,
    "end": 67433
  },
  {
    "name": "Schedolimulus elongatus",
    "start": 67464,
    "end": 67487
  },
  {
    "name": "Schedotermoecia planus",
    "start": 67489,
    "end": 67511
  },
  {
    "name": "Schedotermoecia minutides",
    "start": 67516,
    "end": 67541
  },
  {
    "name": "Schedotermoecia minutus",
    "start": 67606,
    "end": 67629
  },
  {
    "name": "Phorilimulus minutus",
    "start": 67683,
    "end": 67703
  },
  {
    "name": "Schedolimulus",
    "start": 67745,
    "end": 67758
  },
  {
    "name": "Schedorhinotermes translucens",
    "start": 67862,
    "end": 67891
  },
  {
    "name": "Termes translucens",
    "start": 68028,
    "end": 68046
  },
  {
    "name": "Rhinotermes translucens",
    "start": 68091,
    "end": 68114
  },
  {
    "name": "Rhinotermes",
    "start": 68170,
    "end": 68181
  },
  {
    "name": "Schedorhinotermes",
    "start": 68183,
    "end": 68200
  },
  {
    "name": "Rhinotermes",
    "start": 68271,
    "end": 68282
  },
  {
    "name": "Schedorhinotermes",
    "start": 68284,
    "end": 68301
  },
  {
    "name": "Rhinotermes",
    "start": 68373,
    "end": 68384
  },
  {
    "name": "Schedorhinotermes",
    "start": 68386,
    "end": 68403
  },
  {
    "name": "Schedorhinotermes marjoriae",
    "start": 68475,
    "end": 68502
  },
  {
    "name": "Schedorhinotermes celebensis",
    "start": 68554,
    "end": 68582
  },
  {
    "name": "Schedorhinotermes translucens",
    "start": 68636,
    "end": 68665
  },
  {
    "name": "Schedorhinotermes celebensis",
    "start": 68963,
    "end": 68991
  },
  {
    "name": "Schedorhinotermes marjoriae",
    "start": 69105,
    "end": 69132
  },
  {
    "name": "Castanopsis",
    "start": 70395,
    "end": 70406
  },
  {
    "name": "Castanopsis acuminata",
    "start": 70753,
    "end": 70774
  },
  {
    "name": "Schedorhinotermes celebensis",
    "start": 72745,
    "end": 72773
  },
  {
    "name": "Schedorhinotermes celebensis",
    "start": 73009,
    "end": 73037
  },
  {
    "name": "Schedorhinotermes translucens",
    "start": 73042,
    "end": 73071
  },
  {
    "name": "Schedorhinotermes celebensis",
    "start": 73199,
    "end": 73227
  },
  {
    "name": "Schedorhinotermes celebensis",
    "start": 73374,
    "end": 73402
  },
  {
    "name": "Schedorhinotermes translucens",
    "start": 73426,
    "end": 73455
  },
  {
    "name": "Schedorhinotermes marjoriae",
    "start": 73477,
    "end": 73504
  },
  {
    "name": "Schedorhinotermes translucens",
    "start": 73625,
    "end": 73654
  },
  {
    "name": "Schedorhinotermes marjoriae",
    "start": 73786,
    "end": 73813
  },
  {
    "name": "Schedorhinotermes translucens",
    "start": 73818,
    "end": 73847
  },
  {
    "name": "Schedorhinotermes marjoriae",
    "start": 74034,
    "end": 74061
  },
  {
    "name": "Schedorhinotermes translucens",
    "start": 74085,
    "end": 74114
  },
  {
    "name": "Schedorhinotermes translucens",
    "start": 74200,
    "end": 74229
  },
  {
    "name": "Schedorhinotermes seclusus",
    "start": 74588,
    "end": 74614
  },
  {
    "name": "Schedorhinotermes malaccensis",
    "start": 74618,
    "end": 74647
  },
  {
    "name": "Schedorhinotermes longirostris",
    "start": 74651,
    "end": 74681
  },
  {
    "name": "Schedorhinotermes translucens",
    "start": 74847,
    "end": 74876
  },
  {
    "name": "Schedorhinotermes translucens",
    "start": 75265,
    "end": 75294
  },
  {
    "name": "Schedorhinotermes celebensis",
    "start": 75328,
    "end": 75356
  },
  {
    "name": "Schedorhinotermes translucens",
    "start": 76291,
    "end": 76320
  },
  {
    "name": "Schedorhinotermes marjoriae",
    "start": 76369,
    "end": 76396
  },
  {
    "name": "Schedorhinotermes translucens",
    "start": 77268,
    "end": 77297
  },
  {
    "name": "Schedorhinotermes marjoriae",
    "start": 77344,
    "end": 77371
  },
  {
    "name": "Schedorhinotermes longirostris",
    "start": 77868,
    "end": 77898
  },
  {
    "name": "Schedorhinotermes translucens",
    "start": 78114,
    "end": 78143
  },
  {
    "name": "Schedorhinotermes celebensis",
    "start": 78331,
    "end": 78359
  },
  {
    "name": "Myrmedonota termitophila",
    "start": 78524,
    "end": 78548
  },
  {
    "name": "Coleoptera",
    "start": 78550,
    "end": 78560
  },
  {
    "name": "Staphylinidae",
    "start": 78562,
    "end": 78575
  },
  {
    "name": "Aleocharinae",
    "start": 78577,
    "end": 78589
  },
  {
    "name": "Lomechusini",
    "start": 78591,
    "end": 78602
  },
  {
    "name": "Trichopseniini",
    "start": 78683,
    "end": 78697
  },
  {
    "name": "Aleocharinae",
    "start": 78704,
    "end": 78716
  },
  {
    "name": "Schedolimulus elongatus",
    "start": 78786,
    "end": 78809
  },
  {
    "name": "Schedolimulus latus",
    "start": 78811,
    "end": 78830
  },
  {
    "name": "Schedolimulus planus",
    "start": 78832,
    "end": 78852
  },
  {
    "name": "Schizelythron papuanum",
    "start": 78858,
    "end": 78880
  },
  {
    "name": "Prorhinotermes",
    "start": 78988,
    "end": 79002
  },
  {
    "name": "Prorhinotermes",
    "start": 79084,
    "end": 79098
  },
  {
    "name": "Prorhinotermes inopinatus",
    "start": 79229,
    "end": 79254
  },
  {
    "name": "Prorhinotermes",
    "start": 80144,
    "end": 80158
  },
  {
    "name": "Prorhinotermes inopinatus",
    "start": 80545,
    "end": 80570
  },
  {
    "name": "Prorhinotermes inopinatus",
    "start": 80706,
    "end": 80731
  },
  {
    "name": "Prorhinotermes manni",
    "start": 80781,
    "end": 80801
  },
  {
    "name": "Prorhinotermes solomonensis",
    "start": 80877,
    "end": 80904
  },
  {
    "name": "Pandanus",
    "start": 83067,
    "end": 83075
  },
  {
    "name": "Prorhinotermes inopinatus.",
    "start": 84207,
    "end": 84233
  },
  {
    "name": "Termitogeton",
    "start": 85444,
    "end": 85456
  },
  {
    "name": "Termes",
    "start": 85536,
    "end": 85542
  },
  {
    "name": "Termitogeton",
    "start": 85606,
    "end": 85618
  },
  {
    "name": "Termes planus",
    "start": 85757,
    "end": 85770
  },
  {
    "name": "Termes umbilicatus",
    "start": 85932,
    "end": 85950
  },
  {
    "name": "Termitogeton",
    "start": 85983,
    "end": 85995
  },
  {
    "name": "Termitogeton",
    "start": 86080,
    "end": 86092
  },
  {
    "name": "Termes planus",
    "start": 86096,
    "end": 86109
  },
  {
    "name": "Termes umbilicatus",
    "start": 86138,
    "end": 86156
  },
  {
    "name": "Termes planus",
    "start": 86181,
    "end": 86194
  },
  {
    "name": "Termes umbilicatus",
    "start": 86225,
    "end": 86243
  },
  {
    "name": "Termes umbilicatus",
    "start": 86423,
    "end": 86441
  },
  {
    "name": "Termitogeton",
    "start": 86489,
    "end": 86501
  },
  {
    "name": "Termitogeton",
    "start": 86571,
    "end": 86583
  },
  {
    "name": "Termes planus",
    "start": 86654,
    "end": 86667
  },
  {
    "name": "Termes umbilicatus",
    "start": 86762,
    "end": 86780
  },
  {
    "name": "Termes",
    "start": 86808,
    "end": 86814
  },
  {
    "name": "Termitogeton",
    "start": 86816,
    "end": 86828
  },
  {
    "name": "Termes planus",
    "start": 86836,
    "end": 86849
  },
  {
    "name": "Termitogeton",
    "start": 87576,
    "end": 87588
  },
  {
    "name": "Termitogeton planus",
    "start": 87820,
    "end": 87839
  },
  {
    "name": "Termes planus",
    "start": 87973,
    "end": 87986
  },
  {
    "name": "Termes",
    "start": 88056,
    "end": 88062
  },
  {
    "name": "Termitogeton",
    "start": 88064,
    "end": 88076
  },
  {
    "name": "Termitogeton planus",
    "start": 88143,
    "end": 88162
  },
  {
    "name": "Termitogeton",
    "start": 89051,
    "end": 89063
  },
  {
    "name": "Termitogeton planus.",
    "start": 89238,
    "end": 89258
  },
  {
    "name": "Prorhinotermes inopinatus",
    "start": 89620,
    "end": 89645
  },
  {
    "name": "Termitogeton planus",
    "start": 89649,
    "end": 89668
  },
  {
    "name": "Rhinotermitidae",
    "start": 91465,
    "end": 91480
  },
  {
    "name": "Coptotermes",
    "start": 92373,
    "end": 92384
  },
  {
    "name": "Coptotermes elisae",
    "start": 92998,
    "end": 93016
  },
  {
    "name": "Coptotermes pamuae",
    "start": 94022,
    "end": 94040
  },
  {
    "name": "Coptotermes grandiceps",
    "start": 94317,
    "end": 94339
  },
  {
    "name": "Coptotermes remotus",
    "start": 94575,
    "end": 94594
  },
  {
    "name": "Coptotermes gambrinus",
    "start": 94841,
    "end": 94862
  },
  {
    "name": "Termitogeton planus",
    "start": 95110,
    "end": 95129
  },
  {
    "name": "Prorhinotermes inopinatus",
    "start": 95676,
    "end": 95701
  },
  {
    "name": "Heterotermes",
    "start": 95954,
    "end": 95966
  },
  {
    "name": "Heterotermes vagus",
    "start": 96281,
    "end": 96299
  },
  {
    "name": "Heterotermes paradoxus",
    "start": 96611,
    "end": 96633
  },
  {
    "name": "Parrhinotermes",
    "start": 96894,
    "end": 96908
  },
  {
    "name": "Schedorhinotermes",
    "start": 97157,
    "end": 97174
  },
  {
    "name": "Parrhinotermes barbatus",
    "start": 97424,
    "end": 97447
  },
  {
    "name": "Parrhinotermes browni",
    "start": 97708,
    "end": 97729
  },
  {
    "name": "Schedorhinotermes longirostris",
    "start": 97991,
    "end": 98021
  },
  {
    "name": "Schedorhinotermes malaccensis",
    "start": 98550,
    "end": 98579
  },
  {
    "name": "Schedorhinotermes seclusus",
    "start": 99119,
    "end": 99145
  },
  {
    "name": "Schedorhinotermes translucens",
    "start": 99403,
    "end": 99432
  },
  {
    "name": "Rhinotermitidae",
    "start": 99701,
    "end": 99716
  },
  {
    "name": "Rhinotermitidae",
    "start": 100216,
    "end": 100231
  },
  {
    "name": "Rhinotermitidae",
    "start": 101031,
    "end": 101046
  },
  {
    "name": "Rhinotermitidae",
    "start": 101203,
    "end": 101218
  },
  {
    "name": "Heterotermes",
    "start": 101220,
    "end": 101232
  },
  {
    "name": "Coptotermes",
    "start": 101254,
    "end": 101265
  },
  {
    "name": "Reticulitermes",
    "start": 101286,
    "end": 101300
  },
  {
    "name": "Termitidae",
    "start": 101326,
    "end": 101336
  },
  {
    "name": "Macrotermes",
    "start": 101338,
    "end": 101349
  },
  {
    "name": "Cubitermes",
    "start": 101371,
    "end": 101381
  },
  {
    "name": "Parrhinotermes",
    "start": 101775,
    "end": 101789
  },
  {
    "name": "Parrhinotermes browni",
    "start": 101796,
    "end": 101817
  },
  {
    "name": "Parrhinotermes barbatus",
    "start": 101870,
    "end": 101893
  },
  {
    "name": "Heterotermes",
    "start": 101933,
    "end": 101945
  },
  {
    "name": "Niuginitermes",
    "start": 102101,
    "end": 102114
  },
  {
    "name": "Heterotermes vagus",
    "start": 102670,
    "end": 102688
  },
  {
    "name": "Coptotermes pamuae",
    "start": 102693,
    "end": 102711
  },
  {
    "name": "Termitidae",
    "start": 102814,
    "end": 102824
  },
  {
    "name": "Amitermes arboreus",
    "start": 102853,
    "end": 102871
  },
  {
    "name": "Nasutitermes triodiae",
    "start": 102873,
    "end": 102894
  },
  {
    "name": "Microcerotermes taylori",
    "start": 102896,
    "end": 102919
  },
  {
    "name": "Lophotermes aduncus",
    "start": 102921,
    "end": 102940
  },
  {
    "name": "Schedorhinotermes seclusus",
    "start": 103151,
    "end": 103177
  },
  {
    "name": "Ephelotermes cheeli",
    "start": 103195,
    "end": 103214
  },
  {
    "name": "Heterotermes paradoxus",
    "start": 103244,
    "end": 103266
  },
  {
    "name": "Hospitalitermes",
    "start": 103452,
    "end": 103467
  },
  {
    "name": "Microcerotermes piliceps",
    "start": 103559,
    "end": 103583
  },
  {
    "name": "Schedorhinotermes malaccensis",
    "start": 103744,
    "end": 103773
  },
  {
    "name": "Termitogeton planus",
    "start": 103778,
    "end": 103797
  },
  {
    "name": "Termitogeton planus",
    "start": 104605,
    "end": 104624
  },
  {
    "name": "Schedorhinotermes malaccensis",
    "start": 104629,
    "end": 104658
  }
]